r0p3_utils/__init__.py
r0p3_utils/db.py
r0p3_utils-0.1.3.dist-info/METADATA
r0p3_utils-0.1.3.dist-info/WHEEL
r0p3_utils-0.1.3.dist-info/top_level.txt
r0p3_utils-0.1.3.dist-info/RECORD
