Metadata-Version: 2.2
Name: r0p3_utils
Version: 0.1.3
Summary: Package for r0p3 by r0p3
Author-email: Robin Pettersson <robin.pettersson.96@gmail.com>
License: MIT
Keywords: ,
Classifier: Programming Language :: Python :: 3
Classifier: License :: OSI Approved :: MIT License
Classifier: Operating System :: OS Independent
Requires-Python: >=3.12
